[
    {
        "Geoname ID": "2563232",
        "Name": "Attard",
        "ASCII Name": "Attard",
        "Alternate Names": "Attard,Casal Attard,H'Attard,\u0126\u2019Attard,\u0410\u0442\u0442\u0430\u0440\u0434",
        "Feature Class": "P",
        "Feature Code": "PPLA",
        "Country Code": "MT",
        "Country name EN": "Malta",
        "Country Code 2": "",
        "Admin1 Code": "1",
        "Admin2 Code": "",
        "Admin3 Code": "",
        "Admin4 Code": "",
        "Population": "11377",
        "Elevation": "",
        "DIgital Elevation Model": "69",
        "Timezone": "Europe/Malta",
        "Modification date": "Thu Feb 02 2023 05:30:00 GMT+0530 (India Standard Time)",
        "LABEL EN": "Malta",
        "latitude": "35.88972",
        "longitude": "14.4425"
    },
    {
        "Geoname ID": "2563217",
        "Name": "Balzan",
        "ASCII Name": "Balzan",
        "Alternate Names": "Balzan,Casal Balzan,Hal Balzan,\u0126al Balzan",
        "Feature Class": "P",
        "Feature Code": "PPLA",
        "Country Code": "MT",
        "Country name EN": "Malta",
        "Country Code 2": "",
        "Admin1 Code": "2",
        "Admin2 Code": "",
        "Admin3 Code": "",
        "Admin4 Code": "",
        "Population": "4689",
        "Elevation": "",
        "DIgital Elevation Model": "51",
        "Timezone": "Europe/Malta",
        "Modification date": "Fri Feb 03 2023 05:30:00 GMT+0530 (India Standard Time)",
        "LABEL EN": "Malta",
        "latitude": "35.90028",
        "longitude": "14.455"
    },
    {
        "Geoname ID": "2563191",
        "Name": "Birkirkara",
        "ASCII Name": "Birkirkara",
        "Alternate Names": "B'Kara,Birchircara,Birkirkara,B\u2019Kara,Casal Birchircara,byrqyrqrh,\u0411\u0438\u0440\u043a\u0438\u0440\u043a\u0430\u0440\u0430,\u05d1\u05d9\u05e8\u05e7\u05d9\u05e8\u05e7\u05e8\u05d4,\u1262\u122d\u12aa\u122d\u12ab\u122b",
        "Feature Class": "P",
        "Feature Code": "PPLA",
        "Country Code": "MT",
        "Country name EN": "Malta",
        "Country Code 2": "",
        "Admin1 Code": "4",
        "Admin2 Code": "",
        "Admin3 Code": "",
        "Admin4 Code": "",
        "Population": "24356",
        "Elevation": "",
        "DIgital Elevation Model": "41",
        "Timezone": "Europe/Malta",
        "Modification date": "Wed Feb 01 2023 05:30:00 GMT+0530 (India Standard Time)",
        "LABEL EN": "Malta",
        "latitude": "35.89722",
        "longitude": "14.46111"
    },
    {
        "Geoname ID": "2563189",
        "Name": "Bir\u017cebbu\u0121a",
        "ASCII Name": "Birzebbuga",
        "Alternate Names": "B'Buga,B'Bugia,Birzbbu,Birzebbu,Birzebbudzha,Birzebbuga,Birzebbugia,Birzebuggia,Bir\u017cebbu\u0121a,B\u2019Bugia,B\u2019Bu\u0121a,bi er ze bu jia,\u0411\u0438\u0440\u0437\u0435\u0431\u0431\u0443\u0434\u0436\u0430,\u6bd4\u5c14\u6cfd\u5e03\u8d3e",
        "Feature Class": "P",
        "Feature Code": "PPLA",
        "Country Code": "MT",
        "Country name EN": "Malta",
        "Country Code 2": "",
        "Admin1 Code": "5",
        "Admin2 Code": "",
        "Admin3 Code": "",
        "Admin4 Code": "",
        "Population": "12915",
        "Elevation": "",
        "DIgital Elevation Model": "20",
        "Timezone": "Europe/Malta",
        "Modification date": "Thu Feb 02 2023 05:30:00 GMT+0530 (India Standard Time)",
        "LABEL EN": "Malta",
        "latitude": "35.82583",
        "longitude": "14.52694"
    },
    {
        "Geoname ID": "2563181",
        "Name": "Cospicua",
        "ASCII Name": "Cospicua",
        "Alternate Names": "Bormla,Cospicua,Cospiosa,Kospikoua,boleumla,kaspykwa,ke si pi kua,kwsbykw,kwspykwa,\u039a\u03bf\u03c3\u03c0\u03af\u03ba\u03bf\u03c5\u03b1,\u0411\u043e\u0440\u043c\u043b\u0430,\u0532\u0578\u0580\u0574\u056c\u0561,\u0643\u0648\u0633\u0628\u064a\u0643\u0648,\u06a9\u0627\u0633\u067e\u06cc\u06a9\u0648\u0627,\u06a9\u0648\u0633\u067e\u06cc\u06a9\u0648\u0627,\u06a9\u06c6\u0633\u067e\u06cc\u06a9\u0648\u0627,\u79d1\u65af\u76ae\u5938,\ubcf4\ub984\ub77c",
        "Feature Class": "P",
        "Feature Code": "PPLA",
        "Country Code": "MT",
        "Country name EN": "Malta",
        "Country Code 2": "",
        "Admin1 Code": "6",
        "Admin2 Code": "",
        "Admin3 Code": "",
        "Admin4 Code": "",
        "Population": "6096",
        "Elevation": "",
        "DIgital Elevation Model": "39",
        "Timezone": "Europe/Malta",
        "Modification date": "Thu Nov 09 2023 05:30:00 GMT+0530 (India Standard Time)",
        "LABEL EN": "Malta",
        "latitude": "35.88556",
        "longitude": "14.5275"
    },
    {
        "Geoname ID": "2563140",
        "Name": "Dingli",
        "ASCII Name": "Dingli",
        "Alternate Names": "Casal Dingli,Dingli,Had-Dingli,\u0126ad-Dingli",
        "Feature Class": "P",
        "Feature Code": "PPLA",
        "Country Code": "MT",
        "Country name EN": "Malta",
        "Country Code 2": "",
        "Admin1 Code": "7",
        "Admin2 Code": "",
        "Admin3 Code": "",
        "Admin4 Code": "",
        "Population": "3711",
        "Elevation": "",
        "DIgital Elevation Model": "231",
        "Timezone": "Europe/Malta",
        "Modification date": "Fri Feb 03 2023 05:30:00 GMT+0530 (India Standard Time)",
        "LABEL EN": "Malta",
        "latitude": "35.86139",
        "longitude": "14.38222"
    },
    {
        "Geoname ID": "2563115",
        "Name": "Fgura",
        "ASCII Name": "Fgura",
        "Alternate Names": "Fgura,Figura,Il-Fgura,Kunsill Lokali Fgura,fgwra,fu gu la,peugula,\u0424\u0433\u0443\u0440\u0430,\u0641\u06af\u0648\u0631\u0627,\u5f17\u53e4\u62c9,\ud504\uad6c\ub77c",
        "Feature Class": "P",
        "Feature Code": "PPL",
        "Country Code": "MT",
        "Country name EN": "Malta",
        "Country Code 2": "",
        "Admin1 Code": "8",
        "Admin2 Code": "",
        "Admin3 Code": "",
        "Admin4 Code": "",
        "Population": "12877",
        "Elevation": "",
        "DIgital Elevation Model": "64",
        "Timezone": "Europe/Malta",
        "Modification date": "Sun Apr 25 2021 05:30:00 GMT+0530 (India Standard Time)",
        "LABEL EN": "Malta",
        "latitude": "35.87028",
        "longitude": "14.51333"
    },
    {
        "Geoname ID": "2562955",
        "Name": "Floriana",
        "ASCII Name": "Floriana",
        "Alternate Names": "Floriana,Furjana,Il-Furjana,flwryana,peulloliana,\u03a6\u03bb\u03bf\u03c1\u03b9\u03ac\u03bd\u03b1,\u0424\u043b\u043e\u0440\u0438\u0430\u043d\u0430,\u0424\u043b\u043e\u0440\u0456\u0430\u043d\u0430,\u05e4\u05dc\u05d5\u05e8\u05d9\u05d0\u05e0\u05d4,\u0641\u0644\u0648\u0631\u06cc\u0627\u0646\u0627,\ud50c\ub85c\ub9ac\uc544\ub098",
        "Feature Class": "P",
        "Feature Code": "PPLA",
        "Country Code": "MT",
        "Country name EN": "Malta",
        "Country Code 2": "",
        "Admin1 Code": "9",
        "Admin2 Code": "",
        "Admin3 Code": "",
        "Admin4 Code": "",
        "Population": "2032",
        "Elevation": "",
        "DIgital Elevation Model": "47",
        "Timezone": "Europe/Malta",
        "Modification date": "Thu Feb 02 2023 05:30:00 GMT+0530 (India Standard Time)",
        "LABEL EN": "Malta",
        "latitude": "35.89583",
        "longitude": "14.50833"
    },
    {
        "Geoname ID": "8337342",
        "Name": "Fontana",
        "ASCII Name": "Fontana",
        "Alternate Names": "Fontana",
        "Feature Class": "P",
        "Feature Code": "PPLA",
        "Country Code": "MT",
        "Country name EN": "Malta",
        "Country Code 2": "",
        "Admin1 Code": "10",
        "Admin2 Code": "",
        "Admin3 Code": "",
        "Admin4 Code": "",
        "Population": "922",
        "Elevation": "",
        "DIgital Elevation Model": "71",
        "Timezone": "Europe/Malta",
        "Modification date": "Fri Feb 03 2023 05:30:00 GMT+0530 (India Standard Time)",
        "LABEL EN": "Malta",
        "latitude": "36.0375",
        "longitude": "14.23611"
    },
    {
        "Geoname ID": "2563081",
        "Name": "G\u0127ajnsielem",
        "ASCII Name": "Ghajnsielem",
        "Alternate Names": "Ainsielem,Ghain Sielem,Ghajnsielem,G\u0127ajnsielem",
        "Feature Class": "P",
        "Feature Code": "PPLA",
        "Country Code": "MT",
        "Country name EN": "Malta",
        "Country Code 2": "",
        "Admin1 Code": "11",
        "Admin2 Code": "",
        "Admin3 Code": "",
        "Admin4 Code": "",
        "Population": "2931",
        "Elevation": "",
        "DIgital Elevation Model": "78",
        "Timezone": "Europe/Malta",
        "Modification date": "Fri Feb 03 2023 05:30:00 GMT+0530 (India Standard Time)",
        "LABEL EN": "Malta",
        "latitude": "36.02639",
        "longitude": "14.285"
    },
    {
        "Geoname ID": "2563063",
        "Name": "G\u0127arb",
        "ASCII Name": "Gharb",
        "Alternate Names": "Gharb,G\u0127arb,Il-Gharb,Il-G\u0127arb",
        "Feature Class": "P",
        "Feature Code": "PPLA",
        "Country Code": "MT",
        "Country name EN": "Malta",
        "Country Code 2": "",
        "Admin1 Code": "12",
        "Admin2 Code": "",
        "Admin3 Code": "",
        "Admin4 Code": "",
        "Population": "1298",
        "Elevation": "",
        "DIgital Elevation Model": "121",
        "Timezone": "Europe/Malta",
        "Modification date": "Fri Feb 03 2023 05:30:00 GMT+0530 (India Standard Time)",
        "LABEL EN": "Malta",
        "latitude": "36.06",
        "longitude": "14.20889"
    },
    {
        "Geoname ID": "2563046",
        "Name": "G\u0127axaq",
        "ASCII Name": "Ghaxaq",
        "Alternate Names": "Ashiak,Axiak,Casal Asciak,Ghashiak,Ghaxaq,G\u0127axaq,Hal Ghaxaq,Hal Ghaxiak,\u0126al G\u0127axaq",
        "Feature Class": "P",
        "Feature Code": "PPLA",
        "Country Code": "MT",
        "Country name EN": "Malta",
        "Country Code 2": "",
        "Admin1 Code": "15",
        "Admin2 Code": "",
        "Admin3 Code": "",
        "Admin4 Code": "",
        "Population": "4860",
        "Elevation": "",
        "DIgital Elevation Model": "73",
        "Timezone": "Europe/Malta",
        "Modification date": "Fri Feb 03 2023 05:30:00 GMT+0530 (India Standard Time)",
        "LABEL EN": "Malta",
        "latitude": "35.84889",
        "longitude": "14.51667"
    },
    {
        "Geoname ID": "2563020",
        "Name": "Gudja",
        "ASCII Name": "Gudja",
        "Alternate Names": "Gudia,Gudja,Il-Gudja,MLA",
        "Feature Class": "P",
        "Feature Code": "PPLA",
        "Country Code": "MT",
        "Country name EN": "Malta",
        "Country Code 2": "",
        "Admin1 Code": "16",
        "Admin2 Code": "",
        "Admin3 Code": "",
        "Admin4 Code": "",
        "Population": "3184",
        "Elevation": "",
        "DIgital Elevation Model": "79",
        "Timezone": "Europe/Malta",
        "Modification date": "Fri Feb 03 2023 05:30:00 GMT+0530 (India Standard Time)",
        "LABEL EN": "Malta",
        "latitude": "35.84917",
        "longitude": "14.50306"
    },
    {
        "Geoname ID": "2562946",
        "Name": "G\u017cira",
        "ASCII Name": "Gzira",
        "Alternate Names": "Gzira,G\u017cira,Il-Gzira,Il-G\u017cira,\u0413\u0437\u0438\u0440\u0430",
        "Feature Class": "P",
        "Feature Code": "PPLA",
        "Country Code": "MT",
        "Country name EN": "Malta",
        "Country Code 2": "",
        "Admin1 Code": "17",
        "Admin2 Code": "",
        "Admin3 Code": "",
        "Admin4 Code": "",
        "Population": "11669",
        "Elevation": "",
        "DIgital Elevation Model": "31",
        "Timezone": "Europe/Malta",
        "Modification date": "Fri Feb 03 2023 05:30:00 GMT+0530 (India Standard Time)",
        "LABEL EN": "Malta",
        "latitude": "35.90583",
        "longitude": "14.48806"
    },
    {
        "Geoname ID": "2563062",
        "Name": "Hal Gharghur",
        "ASCII Name": "Hal Gharghur",
        "Alternate Names": "Gharghur,G\u0127arg\u0127ur",
        "Feature Class": "P",
        "Feature Code": "PPLA",
        "Country Code": "MT",
        "Country name EN": "Malta",
        "Country Code 2": "",
        "Admin1 Code": "13",
        "Admin2 Code": "",
        "Admin3 Code": "",
        "Admin4 Code": "",
        "Population": "2857",
        "Elevation": "",
        "DIgital Elevation Model": "132",
        "Timezone": "Europe/Malta",
        "Modification date": "Fri Feb 03 2023 05:30:00 GMT+0530 (India Standard Time)",
        "LABEL EN": "Malta",
        "latitude": "35.92409",
        "longitude": "14.45118"
    },
    {
        "Geoname ID": "2562998",
        "Name": "\u0126amrun",
        "ASCII Name": "Hamrun",
        "Alternate Names": "Ham Rum,Hamrun,Il-Hamrun,\u0126amrun",
        "Feature Class": "P",
        "Feature Code": "PPLA",
        "Country Code": "MT",
        "Country name EN": "Malta",
        "Country Code 2": "",
        "Admin1 Code": "18",
        "Admin2 Code": "",
        "Admin3 Code": "",
        "Admin4 Code": "",
        "Population": "9743",
        "Elevation": "",
        "DIgital Elevation Model": "44",
        "Timezone": "Europe/Malta",
        "Modification date": "Fri Feb 03 2023 05:30:00 GMT+0530 (India Standard Time)",
        "LABEL EN": "Malta",
        "latitude": "35.88472",
        "longitude": "14.48444"
    },
    {
        "Geoname ID": "2562261",
        "Name": "Haz-Zebbug",
        "ASCII Name": "Haz-Zebbug",
        "Alternate Names": "Haz-Zebbug,Lebbug,Zebbudzh,\u0126a\u017c-\u017bebbu\u0121,\u0417\u0435\u0431\u0431\u0443\u0434\u0436",
        "Feature Class": "P",
        "Feature Code": "PPLA",
        "Country Code": "MT",
        "Country name EN": "Malta",
        "Country Code 2": "",
        "Admin1 Code": "65",
        "Admin2 Code": "",
        "Admin3 Code": "",
        "Admin4 Code": "",
        "Population": "11079",
        "Elevation": "",
        "DIgital Elevation Model": "100",
        "Timezone": "Europe/Malta",
        "Modification date": "Thu Feb 02 2023 05:30:00 GMT+0530 (India Standard Time)",
        "LABEL EN": "Malta",
        "latitude": "35.87194",
        "longitude": "14.44111"
    },
    {
        "Geoname ID": "2562746",
        "Name": "Imdina",
        "ASCII Name": "Imdina",
        "Alternate Names": "Citta Notabile,Citta Vecchia,Citta Vechia,Citt\u00e0 Notabile,Imdina,L-Imdina,Mdina,Mdina a Rabat,Medina Notabile,Melita,Notabile,\u041c\u0434\u0438\u043d\u0430",
        "Feature Class": "P",
        "Feature Code": "PPLA",
        "Country Code": "MT",
        "Country name EN": "Malta",
        "Country Code 2": "",
        "Admin1 Code": "20",
        "Admin2 Code": "",
        "Admin3 Code": "",
        "Admin4 Code": "",
        "Population": "193",
        "Elevation": "",
        "DIgital Elevation Model": "198",
        "Timezone": "Europe/Malta",
        "Modification date": "Thu Feb 02 2023 05:30:00 GMT+0530 (India Standard Time)",
        "LABEL EN": "Malta",
        "latitude": "35.88694",
        "longitude": "14.4025"
    },
    {
        "Geoname ID": "2562735",
        "Name": "Im\u0121arr",
        "ASCII Name": "Imgarr",
        "Alternate Names": "Imgarr,Imgiar,Imjar,Im\u0121arr,L-Mgarr,L-M\u0121arr,Mgar,Mgarr,M\u0121arr,\u041c\u0433\u0430\u0440",
        "Feature Class": "P",
        "Feature Code": "PPLA",
        "Country Code": "MT",
        "Country name EN": "Malta",
        "Country Code 2": "",
        "Admin1 Code": "21",
        "Admin2 Code": "",
        "Admin3 Code": "",
        "Admin4 Code": "",
        "Population": "3802",
        "Elevation": "",
        "DIgital Elevation Model": "110",
        "Timezone": "Europe/Malta",
        "Modification date": "Fri Feb 03 2023 05:30:00 GMT+0530 (India Standard Time)",
        "LABEL EN": "Malta",
        "latitude": "35.92056",
        "longitude": "14.36639"
    },
    {
        "Geoname ID": "2562698",
        "Name": "Imsida",
        "ASCII Name": "Imsida",
        "Alternate Names": "Imsida,L-Imsida,Misida,Msida,\u041c\u0441\u0438\u0434\u0430",
        "Feature Class": "P",
        "Feature Code": "PPLA",
        "Country Code": "MT",
        "Country name EN": "Malta",
        "Country Code 2": "",
        "Admin1 Code": "23",
        "Admin2 Code": "",
        "Admin3 Code": "",
        "Admin4 Code": "",
        "Population": "13713",
        "Elevation": "",
        "DIgital Elevation Model": "39",
        "Timezone": "Europe/Malta",
        "Modification date": "Fri Feb 03 2023 05:30:00 GMT+0530 (India Standard Time)",
        "LABEL EN": "Malta",
        "latitude": "35.8925",
        "longitude": "14.48278"
    },
    {
        "Geoname ID": "2562694",
        "Name": "Imtarfa",
        "ASCII Name": "Imtarfa",
        "Alternate Names": "Imtarfa,Imtarfa Barracks,L-Imtarfa,Mtarfa",
        "Feature Class": "P",
        "Feature Code": "PPLA",
        "Country Code": "MT",
        "Country name EN": "Malta",
        "Country Code 2": "",
        "Admin1 Code": "24",
        "Admin2 Code": "",
        "Admin3 Code": "",
        "Admin4 Code": "",
        "Population": "2615",
        "Elevation": "",
        "DIgital Elevation Model": "195",
        "Timezone": "Europe/Malta",
        "Modification date": "Fri Feb 03 2023 05:30:00 GMT+0530 (India Standard Time)",
        "LABEL EN": "Malta",
        "latitude": "35.89333",
        "longitude": "14.39889"
    },
    {
        "Geoname ID": "2562830",
        "Name": "Kalkara",
        "ASCII Name": "Kalkara",
        "Alternate Names": "Calcara,Il-Kalkara,Kalkara",
        "Feature Class": "P",
        "Feature Code": "PPLA",
        "Country Code": "MT",
        "Country name EN": "Malta",
        "Country Code 2": "",
        "Admin1 Code": "26",
        "Admin2 Code": "",
        "Admin3 Code": "",
        "Admin4 Code": "",
        "Population": "3059",
        "Elevation": "",
        "DIgital Elevation Model": "34",
        "Timezone": "Europe/Malta",
        "Modification date": "Fri Feb 03 2023 05:30:00 GMT+0530 (India Standard Time)",
        "LABEL EN": "Malta",
        "latitude": "35.88917",
        "longitude": "14.53278"
    },
    {
        "Geoname ID": "2562816",
        "Name": "Ker\u010bem",
        "ASCII Name": "Kercem",
        "Alternate Names": "Kercem,Kerchem,Ker\u010bem",
        "Feature Class": "P",
        "Feature Code": "PPLA",
        "Country Code": "MT",
        "Country name EN": "Malta",
        "Country Code 2": "",
        "Admin1 Code": "27",
        "Admin2 Code": "",
        "Admin3 Code": "",
        "Admin4 Code": "",
        "Population": "1627",
        "Elevation": "",
        "DIgital Elevation Model": "111",
        "Timezone": "Europe/Malta",
        "Modification date": "Thu Jun 11 2020 05:30:00 GMT+0530 (India Standard Time)",
        "LABEL EN": "Malta",
        "latitude": "36.04194",
        "longitude": "14.22667"
    },
    {
        "Geoname ID": "2562815",
        "Name": "Kirkop",
        "ASCII Name": "Kirkop",
        "Alternate Names": "Casal Chircop,Hal-Kirkop,Kirkop,\u0126al-Kirkop",
        "Feature Class": "P",
        "Feature Code": "PPLA",
        "Country Code": "MT",
        "Country name EN": "Malta",
        "Country Code 2": "",
        "Admin1 Code": "28",
        "Admin2 Code": "",
        "Admin3 Code": "",
        "Admin4 Code": "",
        "Population": "2397",
        "Elevation": "",
        "DIgital Elevation Model": "82",
        "Timezone": "Europe/Malta",
        "Modification date": "Fri Feb 03 2023 05:30:00 GMT+0530 (India Standard Time)",
        "LABEL EN": "Malta",
        "latitude": "35.84222",
        "longitude": "14.48528"
    },
    {
        "Geoname ID": "2562800",
        "Name": "L-Iklin",
        "ASCII Name": "L-Iklin",
        "Alternate Names": "Iklin,L'Inglin,L-Iclin",
        "Feature Class": "P",
        "Feature Code": "PPLA",
        "Country Code": "MT",
        "Country name EN": "Malta",
        "Country Code 2": "",
        "Admin1 Code": "19",
        "Admin2 Code": "",
        "Admin3 Code": "",
        "Admin4 Code": "",
        "Population": "3422",
        "Elevation": "",
        "DIgital Elevation Model": "62",
        "Timezone": "Europe/Malta",
        "Modification date": "Fri Feb 03 2023 05:30:00 GMT+0530 (India Standard Time)",
        "LABEL EN": "Malta",
        "latitude": "35.90414",
        "longitude": "14.45415"
    },
    {
        "Geoname ID": "2562801",
        "Name": "Lija",
        "ASCII Name": "Lija",
        "Alternate Names": "Casal Lia,Hal Lija,Lia,Lidza,Lid\u017ea,Lija,liya,lyya,\u0126al Lija,\u0644\u06cc\u06cc\u0627,\ub9ac\uc57c",
        "Feature Class": "P",
        "Feature Code": "PPLA",
        "Country Code": "MT",
        "Country name EN": "Malta",
        "Country Code 2": "",
        "Admin1 Code": "29",
        "Admin2 Code": "",
        "Admin3 Code": "",
        "Admin4 Code": "",
        "Population": "3202",
        "Elevation": "",
        "DIgital Elevation Model": "69",
        "Timezone": "Europe/Malta",
        "Modification date": "Fri Feb 03 2023 05:30:00 GMT+0530 (India Standard Time)",
        "LABEL EN": "Malta",
        "latitude": "35.90056",
        "longitude": "14.44639"
    },
    {
        "Geoname ID": "2562788",
        "Name": "Luqa",
        "ASCII Name": "Luqa",
        "Alternate Names": "Casal Luca,Hal Luqa,Luca,Luqa,MLA,\u0126al Luqa",
        "Feature Class": "P",
        "Feature Code": "PPLA",
        "Country Code": "MT",
        "Country name EN": "Malta",
        "Country Code 2": "",
        "Admin1 Code": "30",
        "Admin2 Code": "",
        "Admin3 Code": "",
        "Admin4 Code": "",
        "Population": "6162",
        "Elevation": "",
        "DIgital Elevation Model": "79",
        "Timezone": "Europe/Malta",
        "Modification date": "Fri Feb 03 2023 05:30:00 GMT+0530 (India Standard Time)",
        "LABEL EN": "Malta",
        "latitude": "35.85889",
        "longitude": "14.48861"
    },
    {
        "Geoname ID": "2562755",
        "Name": "Marsa",
        "ASCII Name": "Marsa",
        "Alternate Names": "Il-Marsa,Marsa,ma er sa,maleusa,marsa,\u039c\u03ac\u03c1\u03c3\u03b1,\u041c\u0430\u0440\u0441\u0430,\u0544\u0561\u0580\u057d\u0561,\u0645\u0627\u0631\u0633\u0627,\u0645\u0627\u0631\u0633\u0627\u060c \u0645\u0627\u0644\u0679\u0627,\u99ac\u723e\u85a9,\ub9c8\ub974\uc0ac",
        "Feature Class": "P",
        "Feature Code": "PPLA",
        "Country Code": "MT",
        "Country name EN": "Malta",
        "Country Code 2": "",
        "Admin1 Code": "31",
        "Admin2 Code": "",
        "Admin3 Code": "",
        "Admin4 Code": "",
        "Population": "5454",
        "Elevation": "",
        "DIgital Elevation Model": "8",
        "Timezone": "Europe/Malta",
        "Modification date": "Thu Feb 02 2023 05:30:00 GMT+0530 (India Standard Time)",
        "LABEL EN": "Malta",
        "latitude": "35.87917",
        "longitude": "14.49528"
    },
    {
        "Geoname ID": "2562750",
        "Name": "Marsaskala",
        "ASCII Name": "Marsaskala",
        "Alternate Names": "M'Skala,Marsa Scala,Marsascala,Marsaskala,Wied il Ghain,Wied il-Ghajn,Wied il-G\u0127ajn,\u041c\u0430\u0440\u0441\u0430\u0441\u043a\u0430\u043b\u0430",
        "Feature Class": "P",
        "Feature Code": "PPLA",
        "Country Code": "MT",
        "Country name EN": "Malta",
        "Country Code 2": "",
        "Admin1 Code": "32",
        "Admin2 Code": "",
        "Admin3 Code": "",
        "Admin4 Code": "",
        "Population": "10024",
        "Elevation": "",
        "DIgital Elevation Model": "30",
        "Timezone": "Europe/Malta",
        "Modification date": "Sat Oct 26 2013 05:30:00 GMT+0530 (India Standard Time)",
        "LABEL EN": "Malta",
        "latitude": "35.8622",
        "longitude": "14.56701"
    },
    {
        "Geoname ID": "2562247",
        "Name": "Marsaxlokk",
        "ASCII Name": "Marsaxlokk",
        "Alternate Names": "M'Xloxx,Marsa Scirocco,Marsa Shlok,Marsashlokk,Marsaxlok,Marsaxlokk,M\u2019Xloxx,\u041c\u0430\u0440\u0441\u0430\u0448\u043b\u043e\u043a\u043a",
        "Feature Class": "P",
        "Feature Code": "PPLA",
        "Country Code": "MT",
        "Country name EN": "Malta",
        "Country Code 2": "",
        "Admin1 Code": "33",
        "Admin2 Code": "",
        "Admin3 Code": "",
        "Admin4 Code": "",
        "Population": "3660",
        "Elevation": "",
        "DIgital Elevation Model": "17",
        "Timezone": "Europe/Malta",
        "Modification date": "Thu Feb 02 2023 05:30:00 GMT+0530 (India Standard Time)",
        "LABEL EN": "Malta",
        "latitude": "35.84194",
        "longitude": "14.54306"
    },
    {
        "Geoname ID": "2562744",
        "Name": "Mellie\u0127a",
        "ASCII Name": "Mellieha",
        "Alternate Names": "Il-Mellieha,Il-Mellie\u0127a,Mellieha,Mellie\u0127a,Mellikha,\u041c\u0435\u043b\u043b\u0438\u0445\u0430",
        "Feature Class": "P",
        "Feature Code": "PPLA",
        "Country Code": "MT",
        "Country name EN": "Malta",
        "Country Code 2": "",
        "Admin1 Code": "34",
        "Admin2 Code": "",
        "Admin3 Code": "",
        "Admin4 Code": "",
        "Population": "11389",
        "Elevation": "",
        "DIgital Elevation Model": "121",
        "Timezone": "Europe/Malta",
        "Modification date": "Fri Feb 03 2023 05:30:00 GMT+0530 (India Standard Time)",
        "LABEL EN": "Malta",
        "latitude": "35.95639",
        "longitude": "14.36222"
    },
    {
        "Geoname ID": "2562734",
        "Name": "M\u0121arr",
        "ASCII Name": "Mgarr",
        "Alternate Names": "Imjar,L-Imgarr,L-Im\u0121arr,Mgarr,M\u0121arr",
        "Feature Class": "P",
        "Feature Code": "PPL",
        "Country Code": "MT",
        "Country name EN": "Malta",
        "Country Code 2": "",
        "Admin1 Code": "21",
        "Admin2 Code": "",
        "Admin3 Code": "",
        "Admin4 Code": "",
        "Population": "2868",
        "Elevation": "",
        "DIgital Elevation Model": "38",
        "Timezone": "Europe/Malta",
        "Modification date": "Tue Apr 17 2018 05:30:00 GMT+0530 (India Standard Time)",
        "LABEL EN": "Malta",
        "latitude": "36.02528",
        "longitude": "14.295"
    },
    {
        "Geoname ID": "2562704",
        "Name": "Mosta",
        "ASCII Name": "Mosta",
        "Alternate Names": "Il-Mosta,Masta,Mosta,Musta,\u041c\u043e\u0441\u0442\u0430",
        "Feature Class": "P",
        "Feature Code": "PPLA",
        "Country Code": "MT",
        "Country name EN": "Malta",
        "Country Code 2": "",
        "Admin1 Code": "35",
        "Admin2 Code": "",
        "Admin3 Code": "",
        "Admin4 Code": "",
        "Population": "23482",
        "Elevation": "",
        "DIgital Elevation Model": "80",
        "Timezone": "Europe/Malta",
        "Modification date": "Wed Feb 01 2023 05:30:00 GMT+0530 (India Standard Time)",
        "LABEL EN": "Malta",
        "latitude": "35.90917",
        "longitude": "14.42556"
    },
    {
        "Geoname ID": "2562701",
        "Name": "Mqabba",
        "ASCII Name": "Mqabba",
        "Alternate Names": "Casal Micabiba,Imkabba,L-Imqabba,Micabba",
        "Feature Class": "P",
        "Feature Code": "PPLA",
        "Country Code": "MT",
        "Country name EN": "Malta",
        "Country Code 2": "",
        "Admin1 Code": "22",
        "Admin2 Code": "",
        "Admin3 Code": "",
        "Admin4 Code": "",
        "Population": "3339",
        "Elevation": "",
        "DIgital Elevation Model": "95",
        "Timezone": "Europe/Malta",
        "Modification date": "Fri Feb 03 2023 05:30:00 GMT+0530 (India Standard Time)",
        "LABEL EN": "Malta",
        "latitude": "35.84763",
        "longitude": "14.46824"
    },
    {
        "Geoname ID": "2562693",
        "Name": "Munxar",
        "ASCII Name": "Munxar",
        "Alternate Names": "Monsciar,Munshar,Munxar",
        "Feature Class": "P",
        "Feature Code": "PPLA",
        "Country Code": "MT",
        "Country name EN": "Malta",
        "Country Code 2": "",
        "Admin1 Code": "36",
        "Admin2 Code": "",
        "Admin3 Code": "",
        "Admin4 Code": "",
        "Population": "840",
        "Elevation": "",
        "DIgital Elevation Model": "80",
        "Timezone": "Europe/Malta",
        "Modification date": "Wed Jul 04 2012 05:30:00 GMT+0530 (India Standard Time)",
        "LABEL EN": "Malta",
        "latitude": "36.03",
        "longitude": "14.23333"
    },
    {
        "Geoname ID": "2562687",
        "Name": "Nadur",
        "ASCII Name": "Nadur",
        "Alternate Names": "In-Nadur,Nadur",
        "Feature Class": "P",
        "Feature Code": "PPLA",
        "Country Code": "MT",
        "Country name EN": "Malta",
        "Country Code 2": "",
        "Admin1 Code": "37",
        "Admin2 Code": "",
        "Admin3 Code": "",
        "Admin4 Code": "",
        "Population": "3933",
        "Elevation": "",
        "DIgital Elevation Model": "161",
        "Timezone": "Europe/Malta",
        "Modification date": "Thu Feb 02 2023 05:30:00 GMT+0530 (India Standard Time)",
        "LABEL EN": "Malta",
        "latitude": "36.03778",
        "longitude": "14.29417"
    },
    {
        "Geoname ID": "2562683",
        "Name": "Naxxar",
        "ASCII Name": "Naxxar",
        "Alternate Names": "In-Naxxar,Nasaras,Nasciar,Nasciaro,Nashar,Naxaro,Naxxar,Na\u0161aras,na sha er,nasar,nashar,nasyaleu,\u0646\u0627\u0633\u0627\u0631,\u0646\u0627\u0634\u0627\u0631,\u7d0d\u6c99\u723e,\ub098\uc0e4\ub974",
        "Feature Class": "P",
        "Feature Code": "PPLA",
        "Country Code": "MT",
        "Country name EN": "Malta",
        "Country Code 2": "",
        "Admin1 Code": "38",
        "Admin2 Code": "",
        "Admin3 Code": "",
        "Admin4 Code": "",
        "Population": "14890",
        "Elevation": "",
        "DIgital Elevation Model": "121",
        "Timezone": "Europe/Malta",
        "Modification date": "Thu Feb 02 2023 05:30:00 GMT+0530 (India Standard Time)",
        "LABEL EN": "Malta",
        "latitude": "35.91361",
        "longitude": "14.44361"
    },
    {
        "Geoname ID": "2562617",
        "Name": "Paola",
        "ASCII Name": "Paola",
        "Alternate Names": "Casal Paola,Casal Paolo,Casal Paula,Paola,Paula,Pawla,Rahal Gdid,Rahal Jedid,Ra\u0127al \u0120did,bao la,paolla,paywla,\u03a0\u03ac\u03bf\u03bb\u03b1,\u041f\u0430\u043e\u043b\u0430,\u067e\u0627\u0626\u0648\u0644\u0627,\u067e\u0627\u0626\u06c6\u0644\u0627,\u067e\u0627\u0648\u0644\u0627\u060c \u0645\u0627\u0644\u0679\u0627,\u4fdd\u62c9,\ud30c\uc62c\ub77c",
        "Feature Class": "P",
        "Feature Code": "PPLA",
        "Country Code": "MT",
        "Country name EN": "Malta",
        "Country Code 2": "",
        "Admin1 Code": "39",
        "Admin2 Code": "",
        "Admin3 Code": "",
        "Admin4 Code": "",
        "Population": "8706",
        "Elevation": "",
        "DIgital Elevation Model": "9",
        "Timezone": "Europe/Malta",
        "Modification date": "Thu Feb 02 2023 05:30:00 GMT+0530 (India Standard Time)",
        "LABEL EN": "Malta",
        "latitude": "35.87306",
        "longitude": "14.49889"
    },
    {
        "Geoname ID": "8337353",
        "Name": "Pembroke",
        "ASCII Name": "Pembroke",
        "Alternate Names": "Pembroke,Pembrukas,Pemproouk,pembeulokeu,\u03a0\u03ad\u03bc\u03c0\u03c1\u03bf\u03bf\u03c5\u03ba,\u067e\u06cc\u0645\u0628\u0631\u0648\u06a9\u060c \u0645\u0627\u0644\u0679\u0627,\ud3a8\ube0c\ub85c\ud06c",
        "Feature Class": "P",
        "Feature Code": "PPLA",
        "Country Code": "MT",
        "Country name EN": "Malta",
        "Country Code 2": "",
        "Admin1 Code": "40",
        "Admin2 Code": "",
        "Admin3 Code": "",
        "Admin4 Code": "",
        "Population": "3842",
        "Elevation": "",
        "DIgital Elevation Model": "41",
        "Timezone": "Europe/Malta",
        "Modification date": "Fri Feb 03 2023 05:30:00 GMT+0530 (India Standard Time)",
        "LABEL EN": "Malta",
        "latitude": "35.93056",
        "longitude": "14.47639"
    },
    {
        "Geoname ID": "2562664",
        "Name": "Piet\u00e0",
        "ASCII Name": "Pieta",
        "Alternate Names": "P'eta,Pieta,Piet\u00e0,Tal-Pieta,Tal-Piet\u00e0,pieta,\u041f\u044c\u0435\u0442\u0430,\u067e\u06cc\u0626\u062a\u0627\u060c \u0645\u0627\u0644\u0679\u0627,\ud53c\uc5d0\ud0c0",
        "Feature Class": "P",
        "Feature Code": "PPLA",
        "Country Code": "MT",
        "Country name EN": "Malta",
        "Country Code 2": "",
        "Admin1 Code": "41",
        "Admin2 Code": "",
        "Admin3 Code": "",
        "Admin4 Code": "",
        "Population": "4892",
        "Elevation": "",
        "DIgital Elevation Model": "30",
        "Timezone": "Europe/Malta",
        "Modification date": "Thu Feb 02 2023 05:30:00 GMT+0530 (India Standard Time)",
        "LABEL EN": "Malta",
        "latitude": "35.89472",
        "longitude": "14.495"
    },
    {
        "Geoname ID": "2562655",
        "Name": "Qala",
        "ASCII Name": "Qala",
        "Alternate Names": "Casal Qala,Il-Qala,Kala,La Cala,Qala,alla,\u0622\u0644\u0627\u060c \u0645\u0627\u0644\u0679\u0627,\uc54c\ub77c",
        "Feature Class": "P",
        "Feature Code": "PPL",
        "Country Code": "MT",
        "Country name EN": "Malta",
        "Country Code 2": "",
        "Admin1 Code": "42",
        "Admin2 Code": "",
        "Admin3 Code": "",
        "Admin4 Code": "",
        "Population": "1929",
        "Elevation": "",
        "DIgital Elevation Model": "112",
        "Timezone": "Europe/Malta",
        "Modification date": "Wed Nov 17 2021 05:30:00 GMT+0530 (India Standard Time)",
        "LABEL EN": "Malta",
        "latitude": "36.03611",
        "longitude": "14.30944"
    },
    {
        "Geoname ID": "2562629",
        "Name": "Qormi",
        "ASCII Name": "Qormi",
        "Alternate Names": "Hal Qormi,Kormi,Kormis,Ormi,awrmy,ge er mi,kwrmy,oleumi,\u0126al Qormi,\u038c\u03c1\u03bc\u03b9,\u041a\u043e\u0440\u043c\u0438,\u041a\u043e\u0440\u043c\u0456,\u0622\u0648\u0631\u0645\u06cc,\u0642\u06c6\u0631\u0645\u06cc,\u06a9\u0648\u0631\u0645\u06cc,\u6208\u723e\u7c73,\uc624\ub974\ubbf8",
        "Feature Class": "P",
        "Feature Code": "PPLA",
        "Country Code": "MT",
        "Country name EN": "Malta",
        "Country Code 2": "",
        "Admin1 Code": "43",
        "Admin2 Code": "",
        "Admin3 Code": "",
        "Admin4 Code": "",
        "Population": "16801",
        "Elevation": "",
        "DIgital Elevation Model": "41",
        "Timezone": "Europe/Malta",
        "Modification date": "Wed Feb 01 2023 05:30:00 GMT+0530 (India Standard Time)",
        "LABEL EN": "Malta",
        "latitude": "35.87601",
        "longitude": "14.472"
    },
    {
        "Geoname ID": "2562622",
        "Name": "Qrendi",
        "ASCII Name": "Qrendi",
        "Alternate Names": "Casal Krendi,Crendi,Il-Qrendi,Krendi,Krendis,Qrendi,aryndy,kui lun di,lendi,\u0622\u0631\u06cc\u0646\u062f\u06cc,\u594e\u502b\u8fea,\ub80c\ub514",
        "Feature Class": "P",
        "Feature Code": "PPLA",
        "Country Code": "MT",
        "Country name EN": "Malta",
        "Country Code 2": "",
        "Admin1 Code": "44",
        "Admin2 Code": "",
        "Admin3 Code": "",
        "Admin4 Code": "",
        "Population": "3148",
        "Elevation": "",
        "DIgital Elevation Model": "110",
        "Timezone": "Europe/Malta",
        "Modification date": "Thu Feb 02 2023 05:30:00 GMT+0530 (India Standard Time)",
        "LABEL EN": "Malta",
        "latitude": "35.83472",
        "longitude": "14.45833"
    },
    {
        "Geoname ID": "2562620",
        "Name": "Rabat",
        "ASCII Name": "Rabat",
        "Alternate Names": "Ir-Rabat,Ir-Rabt,Rabat,Rabatas,Rabato,Rampat,alrabat,la ba te,labateu,rbat  malt,\u03a1\u03b1\u03bc\u03c0\u03ac\u03c4,\u0420\u0430\u0431\u0430\u0442,\u0627\u0644\u0631\u0627\u0628\u0627\u062a,\u0631\u0627\u0628\u0627\u062a\u060c \u0645\u0627\u0644\u0679\u0627,\u0631\u0628\u0627\u062a\u060c \u0645\u0627\u0644\u062a,\u0695\u0627\u0628\u0627\u062a\u060c \u0645\u0627\u06b5\u062a\u0627,\u62c9\u5df4\u7279,\ub77c\ubc14\ud2b8",
        "Feature Class": "P",
        "Feature Code": "PPL",
        "Country Code": "MT",
        "Country name EN": "Malta",
        "Country Code 2": "",
        "Admin1 Code": "45",
        "Admin2 Code": "",
        "Admin3 Code": "",
        "Admin4 Code": "",
        "Population": "11936",
        "Elevation": "",
        "DIgital Elevation Model": "205",
        "Timezone": "Europe/Malta",
        "Modification date": "Wed Feb 01 2023 05:30:00 GMT+0530 (India Standard Time)",
        "LABEL EN": "Malta",
        "latitude": "35.88152",
        "longitude": "14.39872"
    },
    {
        "Geoname ID": "2562598",
        "Name": "Safi",
        "ASCII Name": "Safi",
        "Alternate Names": "Casal Safi,Hal Safi,Safi,\u0126al Safi",
        "Feature Class": "P",
        "Feature Code": "PPLA",
        "Country Code": "MT",
        "Country name EN": "Malta",
        "Country Code 2": "",
        "Admin1 Code": "47",
        "Admin2 Code": "",
        "Admin3 Code": "",
        "Admin4 Code": "",
        "Population": "2280",
        "Elevation": "",
        "DIgital Elevation Model": "106",
        "Timezone": "Europe/Malta",
        "Modification date": "Thu Feb 02 2023 05:30:00 GMT+0530 (India Standard Time)",
        "LABEL EN": "Malta",
        "latitude": "35.83306",
        "longitude": "14.48472"
    },
    {
        "Geoname ID": "2562557",
        "Name": "San \u0120iljan",
        "ASCII Name": "San Giljan",
        "Alternate Names": "Saint Julian,Saint Julian's,San Gilian,San Giljan,San Julian,San Julian's,San Juli\u00e1n,San \u0120ilian,San \u0120iljan,Sent-Dzhulians,St. Julian's,\u0421\u0435\u043d\u0442-\u0414\u0436\u0443\u043b\u0438\u0430\u043d\u0441",
        "Feature Class": "P",
        "Feature Code": "PPLA",
        "Country Code": "MT",
        "Country name EN": "Malta",
        "Country Code 2": "",
        "Admin1 Code": "49",
        "Admin2 Code": "",
        "Admin3 Code": "",
        "Admin4 Code": "",
        "Population": "13792",
        "Elevation": "",
        "DIgital Elevation Model": "19",
        "Timezone": "Europe/Malta",
        "Modification date": "Thu Feb 02 2023 05:30:00 GMT+0530 (India Standard Time)",
        "LABEL EN": "Malta",
        "latitude": "35.91839",
        "longitude": "14.48977"
    },
    {
        "Geoname ID": "2567539",
        "Name": "San \u0120wann",
        "ASCII Name": "San Gwann",
        "Alternate Names": "San Gwann,San \u0120wann",
        "Feature Class": "P",
        "Feature Code": "PPLA",
        "Country Code": "MT",
        "Country name EN": "Malta",
        "Country Code 2": "",
        "Admin1 Code": "48",
        "Admin2 Code": "",
        "Admin3 Code": "",
        "Admin4 Code": "",
        "Population": "14720",
        "Elevation": "",
        "DIgital Elevation Model": "67",
        "Timezone": "Europe/Malta",
        "Modification date": "Wed Feb 01 2023 05:30:00 GMT+0530 (India Standard Time)",
        "LABEL EN": "Malta",
        "latitude": "35.90556",
        "longitude": "14.47611"
    },
    {
        "Geoname ID": "2562552",
        "Name": "San Lawrenz",
        "ASCII Name": "San Lawrenz",
        "Alternate Names": "Saint Lawrence,San Laurenz,San Lawrenz",
        "Feature Class": "P",
        "Feature Code": "PPLA",
        "Country Code": "MT",
        "Country name EN": "Malta",
        "Country Code 2": "",
        "Admin1 Code": "50",
        "Admin2 Code": "",
        "Admin3 Code": "",
        "Admin4 Code": "",
        "Population": "530",
        "Elevation": "",
        "DIgital Elevation Model": "131",
        "Timezone": "Europe/Malta",
        "Modification date": "Wed Dec 15 2021 05:30:00 GMT+0530 (India Standard Time)",
        "LABEL EN": "Malta",
        "latitude": "36.05556",
        "longitude": "14.20361"
    },
    {
        "Geoname ID": "2562541",
        "Name": "San Pawl il-Ba\u0127ar",
        "ASCII Name": "San Pawl il-Bahar",
        "Alternate Names": "Baia di San Paolo,Saint Paul's Bay,San Paul Amere,San Paul a Mare,San Paul \u00e0 Mare,San Pawl il-Bahar,San Pawl il-Ba\u0127ar,St Paul's Bay",
        "Feature Class": "P",
        "Feature Code": "PPLA",
        "Country Code": "MT",
        "Country name EN": "Malta",
        "Country Code 2": "",
        "Admin1 Code": "52",
        "Admin2 Code": "",
        "Admin3 Code": "",
        "Admin4 Code": "",
        "Population": "32042",
        "Elevation": "",
        "DIgital Elevation Model": "22",
        "Timezone": "Europe/Malta",
        "Modification date": "Wed Feb 01 2023 05:30:00 GMT+0530 (India Standard Time)",
        "LABEL EN": "Malta",
        "latitude": "35.95064",
        "longitude": "14.41561"
    },
    {
        "Geoname ID": "2562545",
        "Name": "Sannat",
        "ASCII Name": "Sannat",
        "Alternate Names": "Is-Sannat,Sanatas,Sannat,Ta' Sannat,sanateu,sannat,\u0633\u0627\u0646\u0646\u0627\u062a,\uc0ac\ub098\ud2b8",
        "Feature Class": "P",
        "Feature Code": "PPLA",
        "Country Code": "MT",
        "Country name EN": "Malta",
        "Country Code 2": "",
        "Admin1 Code": "54",
        "Admin2 Code": "",
        "Admin3 Code": "",
        "Admin4 Code": "",
        "Population": "1681",
        "Elevation": "",
        "DIgital Elevation Model": "119",
        "Timezone": "Europe/Malta",
        "Modification date": "Thu Feb 02 2023 05:30:00 GMT+0530 (India Standard Time)",
        "LABEL EN": "Malta",
        "latitude": "36.02444",
        "longitude": "14.24278"
    },
    {
        "Geoname ID": "2562529",
        "Name": "Santa Lu\u010bija",
        "ASCII Name": "Santa Lucija",
        "Alternate Names": "Santa Lucia,Santa Lucija,Santa Lu\u010bija",
        "Feature Class": "P",
        "Feature Code": "PPLX",
        "Country Code": "MT",
        "Country name EN": "Malta",
        "Country Code 2": "",
        "Admin1 Code": "51",
        "Admin2 Code": "",
        "Admin3 Code": "",
        "Admin4 Code": "",
        "Population": "2954",
        "Elevation": "",
        "DIgital Elevation Model": "58",
        "Timezone": "Europe/Malta",
        "Modification date": "Fri Feb 03 2023 05:30:00 GMT+0530 (India Standard Time)",
        "LABEL EN": "Malta",
        "latitude": "35.86278",
        "longitude": "14.5075"
    },
    {
        "Geoname ID": "2562518",
        "Name": "Santa Venera",
        "ASCII Name": "Santa Venera",
        "Alternate Names": "Saint Venera,Santa Venera,Santa Vennera,St. Venera",
        "Feature Class": "P",
        "Feature Code": "PPLA",
        "Country Code": "MT",
        "Country name EN": "Malta",
        "Country Code 2": "",
        "Admin1 Code": "53",
        "Admin2 Code": "",
        "Admin3 Code": "",
        "Admin4 Code": "",
        "Population": "7590",
        "Elevation": "",
        "DIgital Elevation Model": "52",
        "Timezone": "Europe/Malta",
        "Modification date": "Fri Feb 03 2023 05:30:00 GMT+0530 (India Standard Time)",
        "LABEL EN": "Malta",
        "latitude": "35.89083",
        "longitude": "14.47417"
    },
    {
        "Geoname ID": "2562792",
        "Name": "Senglea",
        "ASCII Name": "Senglea",
        "Alternate Names": "Isla,L-Isla,Sen'nklea,Senglea,sen ge lai a,seng-geullea,snjlya,synglya,\u03a3\u03b5\u03bd\u03b3\u03ba\u03bb\u03ad\u03b1,\u0418\u0441\u043b\u0430,\u0421\u0435\u043d\u0433\u043b\u0435\u0430,\u05e1\u05e0\u05d2\u05dc\u05d0\u05d4,\u0633\u0646\u062c\u0644\u064a\u0627,\u0633\u06cc\u0646\u06af\u0644\u06cc\u0627,\u68ee\u683c\u840a\u963f,\uc14d\uae00\ub808\uc544",
        "Feature Class": "P",
        "Feature Code": "PPLA",
        "Country Code": "MT",
        "Country name EN": "Malta",
        "Country Code 2": "",
        "Admin1 Code": "25",
        "Admin2 Code": "",
        "Admin3 Code": "",
        "Admin4 Code": "",
        "Population": "2720",
        "Elevation": "",
        "DIgital Elevation Model": "18",
        "Timezone": "Europe/Malta",
        "Modification date": "Thu Feb 02 2023 05:30:00 GMT+0530 (India Standard Time)",
        "LABEL EN": "Malta",
        "latitude": "35.8875",
        "longitude": "14.51694"
    },
    {
        "Geoname ID": "2562504",
        "Name": "Si\u0121\u0121iewi",
        "ASCII Name": "Siggiewi",
        "Alternate Names": "Is-Siggiewi,Is-Si\u0121\u0121iewi,Sidzivis,Sid\u017eivis,Siggieui,Siggiewi,Sigijevi,Sijuwi,Si\u0121\u0121iewi,Suggeui,sijiwi,sygywy,syjjywy,syjywy,xi jie wei,\u0421\u0438\u0433\u0438\u0458\u0435\u0432\u0438,\u0633\u06cc\u062c\u062c\u06cc\u0648\u06cc,\u0633\u06cc\u062c\u06cc\u0648\u06cc,\u0633\u06cc\u06af\u06cc\u0648\u06cc,\u932b\u5091\u7dad,\uc2dc\uc9c0\uc704",
        "Feature Class": "P",
        "Feature Code": "PPLA",
        "Country Code": "MT",
        "Country name EN": "Malta",
        "Country Code 2": "",
        "Admin1 Code": "55",
        "Admin2 Code": "",
        "Admin3 Code": "",
        "Admin4 Code": "",
        "Population": "8721",
        "Elevation": "",
        "DIgital Elevation Model": "126",
        "Timezone": "Europe/Malta",
        "Modification date": "Thu Feb 02 2023 05:30:00 GMT+0530 (India Standard Time)",
        "LABEL EN": "Malta",
        "latitude": "35.85556",
        "longitude": "14.43639"
    },
    {
        "Geoname ID": "2562501",
        "Name": "Sliema",
        "ASCII Name": "Sliema",
        "Alternate Names": "Sliema,Slijema,Slima,Tas-Sliema,seullima,si li ma,slyma,slymh,\u03a3\u03bb\u03b9\u03ad\u03bc\u03b1,\u0421\u043b\u0438\u043c\u0430,\u0421\u043b\u0438\u0458\u0435\u043c\u0430,\u0421\u043b\u0456\u043c\u0430,\u05e1\u05dc\u05d9\u05de\u05d4,\u0633\u0644\u06cc\u0645\u0627,\u65af\u5229\u99ac,\uc2ac\ub9ac\ub9c8",
        "Feature Class": "P",
        "Feature Code": "PPLA",
        "Country Code": "MT",
        "Country name EN": "Malta",
        "Country Code 2": "",
        "Admin1 Code": "56",
        "Admin2 Code": "",
        "Admin3 Code": "",
        "Admin4 Code": "",
        "Population": "22591",
        "Elevation": "",
        "DIgital Elevation Model": "40",
        "Timezone": "Europe/Malta",
        "Modification date": "Thu Feb 02 2023 05:30:00 GMT+0530 (India Standard Time)",
        "LABEL EN": "Malta",
        "latitude": "35.9125",
        "longitude": "14.50194"
    },
    {
        "Geoname ID": "2562850",
        "Name": "Swieqi",
        "ASCII Name": "Swieqi",
        "Alternate Names": "Is Suieki,Is-Swieki,Is-Swieqi,Sviji,Svikis,Swieqi,seuwii,si wei ji,swyky,swyqy,swyyay,\u0421\u0432\u0438\u0439\u0438,\u0633\u0648\u06cc\u0626\u0627\u06cc,\u0633\u0648\u06cc\u0642\u06cc,\u0633\u0648\u06cc\u06a9\u06cc,\u65af\u7dad\u5409,\uc2a4\uc704\uc774",
        "Feature Class": "P",
        "Feature Code": "PPLA",
        "Country Code": "MT",
        "Country name EN": "Malta",
        "Country Code 2": "",
        "Admin1 Code": "57",
        "Admin2 Code": "",
        "Admin3 Code": "",
        "Admin4 Code": "",
        "Population": "14452",
        "Elevation": "",
        "DIgital Elevation Model": "46",
        "Timezone": "Europe/Malta",
        "Modification date": "Thu Feb 02 2023 05:30:00 GMT+0530 (India Standard Time)",
        "LABEL EN": "Malta",
        "latitude": "35.9225",
        "longitude": "14.48"
    },
    {
        "Geoname ID": "2562320",
        "Name": "Ta\u2019 Xbiex",
        "ASCII Name": "Ta' Xbiex",
        "Alternate Names": "Ta' Shbiesh,Ta' Xbiex,Ta-Shbish,Tas Biesh,Tasbiesch,Ta\u2019 Shbiesh,Ta\u2019 Xbiex,\u0422\u0430-\u0428\u0431\u0438\u0448",
        "Feature Class": "P",
        "Feature Code": "PPLA",
        "Country Code": "MT",
        "Country name EN": "Malta",
        "Country Code 2": "",
        "Admin1 Code": "58",
        "Admin2 Code": "",
        "Admin3 Code": "",
        "Admin4 Code": "",
        "Population": "2012",
        "Elevation": "",
        "DIgital Elevation Model": "21",
        "Timezone": "Europe/Malta",
        "Modification date": "Fri Feb 03 2023 05:30:00 GMT+0530 (India Standard Time)",
        "LABEL EN": "Malta",
        "latitude": "35.89917",
        "longitude": "14.49444"
    },
    {
        "Geoname ID": "2562349",
        "Name": "Tarxien",
        "ASCII Name": "Tarxien",
        "Alternate Names": "Casal Tarxien,Hal Tarxien,Tarscen,Tarshien,Tarshin,Tarsinas,Tarxien,Tar\u0161inas,Tirix,ta er xin,taleusin,tarshyn,tarshyyn,trzyn,\u0126al Tarxien,\u0422\u0430\u0440\u0448\u0438\u043d,\u0422\u0430\u0440\u0448\u0456\u0435\u043d,\u062a\u0627\u0631\u0634\u06cc\u0626\u0646,\u062a\u0627\u0631\u0634\u06cc\u0646,\u062a\u0631\u0632\u06cc\u0646,\u5854\u723e\u6b23,\ud0c0\ub974\uc2e0",
        "Feature Class": "P",
        "Feature Code": "PPLA",
        "Country Code": "MT",
        "Country name EN": "Malta",
        "Country Code 2": "",
        "Admin1 Code": "59",
        "Admin2 Code": "",
        "Admin3 Code": "",
        "Admin4 Code": "",
        "Population": "8627",
        "Elevation": "",
        "DIgital Elevation Model": "62",
        "Timezone": "Europe/Malta",
        "Modification date": "Thu Feb 02 2023 05:30:00 GMT+0530 (India Standard Time)",
        "LABEL EN": "Malta",
        "latitude": "35.86583",
        "longitude": "14.515"
    },
    {
        "Geoname ID": "2562305",
        "Name": "Valletta",
        "ASCII Name": "Valletta",
        "Alternate Names": "A Valeta,A Valletta,Baleta,Baletta,La Valet,La Valeta,La Valeto,La Valetta,La Valette,La Valletta,La Val\u00e8t,La Val\u00ebtta,La-Valeto,MLA,Vaileite,Valeta,Valetta,Valleta,Vallett,Valletta,Valletta osh,Vallettae,Waleta,balleta,baretta,bhaleta,bhalletta,falyta,hua lie ta,valaita,valerra,valletta,vheleta,wa lai ta,wal let ta,walta,wlth,\u0141a Va\u0142eta,\u0392\u03b1\u03bb\u03ad\u03c4\u03b1,\u0392\u03b1\u03bb\u03ad\u03c4\u03c4\u03b1,\u0412\u0430\u043b\u0435\u0442\u0430,\u0412\u0430\u043b\u043b\u0435\u0442\u0442\u00e6,\u0412\u0430\u043b\u043b\u0435\u0442\u0442\u0430,\u0412\u0430\u043b\u043b\u0435\u0442\u0442\u0430 \u043e\u0448,\u041b\u0430 \u0412\u0430\u043b\u0435\u0442\u0430,\u054e\u0561\u056c\u0565\u057f\u0561,\u05d5\u05d5\u05d0\u05dc\u05e2\u05d8\u05d0,\u05d5\u05dc\u05d8\u05d4,\u0641\u0627\u0644\u064a\u062a\u0627,\u0648\u0627\u0644\u062a\u0627,\u0648\u0627\u0644\u06cc\u0679\u0627,\u0648\u0644\u06cc\u0679\u0627,\u06a4\u0627\u0644\u06ce\u062a\u0627,\u092d\u0932\u0947\u091f,\u0935\u094d\u0939\u0945\u0932\u0947\u091f\u093e,\u09ad\u09be\u09b2\u09cd\u09b2\u09c7\u09a4\u09cd\u09a4\u09be,\u0a35\u0a32\u0a48\u0a1f\u0a3e,\u0bb5\u0bb2\u0bcd\u0bb2\u0bc6\u0b9f\u0bcd\u0b9f\u0bbe,\u0d35\u0d32\u0d47\u0d31\u0d4d\u0d31,\u0e27\u0e31\u0e25\u0e40\u0e25\u0e15\u0e15\u0e32,\u0f5d\u0f0b\u0f63\u0f7a\u0f0b\u0f50\u0f0d,\u10d5\u10d0\u10da\u10d4\u10e2\u10d0,\u126b\u120c\u1273,\u30d0\u30ec\u30c3\u30bf,\u74e6\u83b1\u5854,\u83ef\u5217\u4ed6,\ubc1c\ub808\ud0c0",
        "Feature Class": "P",
        "Feature Code": "PPLC",
        "Country Code": "MT",
        "Country name EN": "Malta",
        "Country Code 2": "",
        "Admin1 Code": "60",
        "Admin2 Code": "",
        "Admin3 Code": "",
        "Admin4 Code": "",
        "Population": "6794",
        "Elevation": "",
        "DIgital Elevation Model": "44",
        "Timezone": "Europe/Malta",
        "Modification date": "Tue Oct 29 2019 05:30:00 GMT+0530 (India Standard Time)",
        "LABEL EN": "Malta",
        "latitude": "35.89968",
        "longitude": "14.5148"
    },
    {
        "Geoname ID": "2562619",
        "Name": "Victoria",
        "ASCII Name": "Victoria",
        "Alternate Names": "Ir-Rabat,Rabat,Victoria,Victoria Town,Victoria pa Gozo,Victoria p\u00e5 Gozo,Vict\u00f2ria,Viktori,Viktorija,Vittoria,bigtolia,wei duo li ya,wyktwrya  malt,wyqtwryh,\u0412\u0438\u043a\u0442\u043e\u0440\u0438,\u0412\u0438\u043a\u0442\u043e\u0440\u0438\u044f,\u0412\u0438\u043a\u0442\u043e\u0440\u0438\u0458\u0430,\u0412\u0456\u043a\u0442\u043e\u0440\u0456\u044f,\u0420\u0430\u0431\u0430\u0442,\u05d5\u05d9\u05e7\u05d8\u05d5\u05e8\u05d9\u05d4,\u0648\u06a9\u0679\u0648\u0631\u06cc\u06c1\u060c \u06af\u0648\u0632\u0648,\u0648\u06cc\u06a9\u062a\u0648\u0631\u06cc\u0627\u060c \u0645\u0627\u0644\u062a,\u06a4\u06cc\u06a9\u062a\u06c6\u0631\u06cc\u0627\u060c \u0645\u0627\u06b5\u062a\u0627,\u7dad\u591a\u5229\u4e9e,\ube45\ud1a0\ub9ac\uc544",
        "Feature Class": "P",
        "Feature Code": "PPLA",
        "Country Code": "MT",
        "Country name EN": "Malta",
        "Country Code 2": "",
        "Admin1 Code": "46",
        "Admin2 Code": "",
        "Admin3 Code": "",
        "Admin4 Code": "",
        "Population": "6596",
        "Elevation": "",
        "DIgital Elevation Model": "104",
        "Timezone": "Europe/Malta",
        "Modification date": "Wed Jan 10 2024 05:30:00 GMT+0530 (India Standard Time)",
        "LABEL EN": "Malta",
        "latitude": "36.04444",
        "longitude": "14.23972"
    },
    {
        "Geoname ID": "2562966",
        "Name": "Vittoriosa",
        "ASCII Name": "Vittoriosa",
        "Alternate Names": "Birgu,Il-Birgu,Vittoriosa,Vittorioza,\u0411\u0438\u0440\u0433\u0443,\u0412\u0438\u0442\u0442\u043e\u0440\u0438\u043e\u0437\u0430",
        "Feature Class": "P",
        "Feature Code": "PPLA",
        "Country Code": "MT",
        "Country name EN": "Malta",
        "Country Code 2": "",
        "Admin1 Code": "3",
        "Admin2 Code": "",
        "Admin3 Code": "",
        "Admin4 Code": "",
        "Population": "2489",
        "Elevation": "",
        "DIgital Elevation Model": "-9999",
        "Timezone": "Europe/Malta",
        "Modification date": "Thu Feb 02 2023 05:30:00 GMT+0530 (India Standard Time)",
        "LABEL EN": "Malta",
        "latitude": "35.89222",
        "longitude": "14.51833"
    },
    {
        "Geoname ID": "2562280",
        "Name": "Xag\u0127ra",
        "ASCII Name": "Xaghra",
        "Alternate Names": "Caccia,Ix-Xaghra,Ix-Xag\u0127ra,Kacca,Kacha,Ka\u010b\u010ba,Shaghra,Xaghra,Xag\u0127ra",
        "Feature Class": "P",
        "Feature Code": "PPLA",
        "Country Code": "MT",
        "Country name EN": "Malta",
        "Country Code 2": "",
        "Admin1 Code": "61",
        "Admin2 Code": "",
        "Admin3 Code": "",
        "Admin4 Code": "",
        "Population": "3680",
        "Elevation": "",
        "DIgital Elevation Model": "144",
        "Timezone": "Europe/Malta",
        "Modification date": "Thu Feb 02 2023 05:30:00 GMT+0530 (India Standard Time)",
        "LABEL EN": "Malta",
        "latitude": "36.05",
        "longitude": "14.26444"
    },
    {
        "Geoname ID": "2562274",
        "Name": "Xewkija",
        "ASCII Name": "Xewkija",
        "Alternate Names": "Ix-Xewkija,Seukidza,Showkiya,Xeuchia,Xewkija,shwkyt,shywkya,syeukiya,\u0160eukid\u017ea,\u0634\u0648\u0643\u064a\u0629,\u0634\u06cc\u0648\u06a9\u06cc\u0627,\uc170\uc6b0\ud0a4\uc57c",
        "Feature Class": "P",
        "Feature Code": "PPLA",
        "Country Code": "MT",
        "Country name EN": "Malta",
        "Country Code 2": "",
        "Admin1 Code": "62",
        "Admin2 Code": "",
        "Admin3 Code": "",
        "Admin4 Code": "",
        "Population": "3303",
        "Elevation": "",
        "DIgital Elevation Model": "99",
        "Timezone": "Europe/Malta",
        "Modification date": "Wed Jul 04 2012 05:30:00 GMT+0530 (India Standard Time)",
        "LABEL EN": "Malta",
        "latitude": "36.03278",
        "longitude": "14.25806"
    },
    {
        "Geoname ID": "2562273",
        "Name": "Xg\u0127ajra",
        "ASCII Name": "Xghajra",
        "Alternate Names": "Ix-Xghara,Ix-Xg\u0127ara,Sh'ayra,Shghaira,Sh\u2019ayra,Xghaira,Xghajra,Xg\u0127ajra",
        "Feature Class": "P",
        "Feature Code": "PPLA",
        "Country Code": "MT",
        "Country name EN": "Malta",
        "Country Code 2": "",
        "Admin1 Code": "63",
        "Admin2 Code": "",
        "Admin3 Code": "",
        "Admin4 Code": "",
        "Population": "1830",
        "Elevation": "",
        "DIgital Elevation Model": "31",
        "Timezone": "Europe/Malta",
        "Modification date": "Fri Feb 03 2023 05:30:00 GMT+0530 (India Standard Time)",
        "LABEL EN": "Malta",
        "latitude": "35.88556",
        "longitude": "14.5475"
    },
    {
        "Geoname ID": "2562266",
        "Name": "\u017babbar",
        "ASCII Name": "Zabbar",
        "Alternate Names": "Haz-Zabbar,Ha\u017c-\u017babbar,Zabar,Zabaras,Zabbar,jabaleu,zabar,zha ba er,\u0126a\u017c-\u017babbar,\u017babbar,\u0417\u0430\u0431\u0430\u0440,\u0417\u0430\u0431\u0431\u0430\u0440,\u0632\u0627\u0628\u0627\u0631,\u624e\u5df4\u723e,\uc790\ubc14\ub974",
        "Feature Class": "P",
        "Feature Code": "PPLA",
        "Country Code": "MT",
        "Country name EN": "Malta",
        "Country Code 2": "",
        "Admin1 Code": "64",
        "Admin2 Code": "",
        "Admin3 Code": "",
        "Admin4 Code": "",
        "Population": "15648",
        "Elevation": "",
        "DIgital Elevation Model": "47",
        "Timezone": "Europe/Malta",
        "Modification date": "Wed Feb 01 2023 05:30:00 GMT+0530 (India Standard Time)",
        "LABEL EN": "Malta",
        "latitude": "35.87611",
        "longitude": "14.535"
    },
    {
        "Geoname ID": "2562260",
        "Name": "\u017bebbu\u0121",
        "ASCII Name": "Zebbug",
        "Alternate Names": "Iz-Zebbug,Iz-Zebbug (Gozo),I\u017c-\u017bebbu\u0121,I\u017c-\u017bebbu\u0121 (Gozo),Zebbug,Zebbug (Gozo),Zebbuj,Zebudzas,Zebud\u017eas,jebuji,zybwj  gwzw,\u017bebbu\u0121,\u017bebbu\u0121 (Gozo),\u0632\u06cc\u0628\u0648\u062c\u060c \u06af\u0648\u0632\u0648,\uc81c\ubd80\uc9c0",
        "Feature Class": "P",
        "Feature Code": "PPLA",
        "Country Code": "MT",
        "Country name EN": "Malta",
        "Country Code 2": "",
        "Admin1 Code": "66",
        "Admin2 Code": "",
        "Admin3 Code": "",
        "Admin4 Code": "",
        "Population": "1770",
        "Elevation": "",
        "DIgital Elevation Model": "138",
        "Timezone": "Europe/Malta",
        "Modification date": "Thu Feb 02 2023 05:30:00 GMT+0530 (India Standard Time)",
        "LABEL EN": "Malta",
        "latitude": "36.07222",
        "longitude": "14.23583"
    },
    {
        "Geoname ID": "2562258",
        "Name": "\u017bejtun",
        "ASCII Name": "Zejtun",
        "Alternate Names": "Casal Zeitun,Iz Zeitun,Iz-Zejtun,I\u017c-\u017bejtun,Zeitun,Zeitunas,Zeit\u016bnas,Zejtun,jeitun,zi dun,zytwn  malt,\u017bejtun,\u0417\u0435\u0439\u0442\u0443\u043d,\u0417\u0435\u0458\u0442\u0443\u043d,\u0632\u06cc\u062a\u0648\u0646\u060c \u0645\u0627\u0644\u062a,\u0632\u06cc\u062a\u0648\u0646\u060c \u0645\u0627\u0644\u0679\u0627,\u0632\u06d5\u06cc\u062a\u0648\u0648\u0646\u060c \u0645\u0627\u06b5\u062a\u0627,\u699f\u6a54,\uc81c\uc774\ud230",
        "Feature Class": "P",
        "Feature Code": "PPLA",
        "Country Code": "MT",
        "Country name EN": "Malta",
        "Country Code 2": "",
        "Admin1 Code": "67",
        "Admin2 Code": "",
        "Admin3 Code": "",
        "Admin4 Code": "",
        "Population": "11549",
        "Elevation": "",
        "DIgital Elevation Model": "56",
        "Timezone": "Europe/Malta",
        "Modification date": "Thu Jun 11 2020 05:30:00 GMT+0530 (India Standard Time)",
        "LABEL EN": "Malta",
        "latitude": "35.85583",
        "longitude": "14.53306"
    },
    {
        "Geoname ID": "2562250",
        "Name": "\u017burrieq",
        "ASCII Name": "Zurrieq",
        "Alternate Names": "Casal Zurrico,Iz-Zurrieq,I\u017c-\u017burrieq,Zebbudzh,Zouriek,Zurikas,Zurrico,Zurriek,Zurrieq,Zurrik,julikeu,zu li ge,zwryk,zwryq,zwryya,\u017burrieq,\u0396\u03bf\u03c5\u03c1\u03b9\u03ad\u03ba,\u0417\u0435\u0431\u0431\u0443\u0434\u0436,\u0417\u0443\u0440\u0440\u0438\u043a,\u0417\u0443\u0440\u0440\u0456\u043a,\u0632\u0648\u0631\u06cc\u0626\u0627,\u0632\u0648\u0631\u06cc\u0642,\u0632\u0648\u0631\u06cc\u06a9,\u7956\u91cc\u683c,\uc8fc\ub9ac\ud06c",
        "Feature Class": "P",
        "Feature Code": "PPLA",
        "Country Code": "MT",
        "Country name EN": "Malta",
        "Country Code 2": "",
        "Admin1 Code": "68",
        "Admin2 Code": "",
        "Admin3 Code": "",
        "Admin4 Code": "",
        "Population": "10962",
        "Elevation": "",
        "DIgital Elevation Model": "111",
        "Timezone": "Europe/Malta",
        "Modification date": "Thu Feb 02 2023 05:30:00 GMT+0530 (India Standard Time)",
        "LABEL EN": "Malta",
        "latitude": "35.83111",
        "longitude": "14.47417"
    }
]