[
    {
        "Geoname ID": "1651816",
        "Name": "Aileu",
        "ASCII Name": "Aileu",
        "Alternate Names": "Aileou,Aileu,Ajleu,Vila General Camona,Vila General Carmona,a yi lai wu,aylyw,\u0391\u03ca\u03bb\u03ad\u03bf\u03c5,\u0410\u0439\u043b\u0435\u0443,\u0531\u056b\u056c\u0565\u0578\u0582,\u05d0\u05d9\u05dc\u05d0\u05d5,\u0627\u06cc\u0644\u0626\u0648,\u963f\u4f0a\u840a\u70cf",
        "Feature Class": "P",
        "Feature Code": "PPLA",
        "Country Code": "TL",
        "Country name EN": "Timor-Leste",
        "Country Code 2": "",
        "Admin1 Code": "AL",
        "Admin2 Code": "201",
        "Admin3 Code": "20108",
        "Admin4 Code": "",
        "Population": "17356",
        "Elevation": "913",
        "DIgital Elevation Model": "926",
        "Timezone": "Asia/Dili",
        "Modification date": "Sun Nov 27 2016 05:30:00 GMT+0530 (India Standard Time)",
        "LABEL EN": "Timor-Leste",
        "latitude": "-8.72806",
        "longitude": "125.56639"
    },
    {
        "Geoname ID": "1651810",
        "Name": "Ainaro",
        "ASCII Name": "Ainaro",
        "Alternate Names": "Ainaro,Ainaru,Builico,Dystrykt Ainaro,Hato-Builico,Vila de Ainaro",
        "Feature Class": "P",
        "Feature Code": "PPLA",
        "Country Code": "TL",
        "Country name EN": "Timor-Leste",
        "Country Code 2": "",
        "Admin1 Code": "AN",
        "Admin2 Code": "101",
        "Admin3 Code": "10101",
        "Admin4 Code": "",
        "Population": "12000",
        "Elevation": "",
        "DIgital Elevation Model": "820",
        "Timezone": "Asia/Dili",
        "Modification date": "Sun Nov 27 2016 05:30:00 GMT+0530 (India Standard Time)",
        "LABEL EN": "Timor-Leste",
        "latitude": "-8.99241",
        "longitude": "125.50816"
    },
    {
        "Geoname ID": "1649539",
        "Name": "Baukau",
        "ASCII Name": "Baukau",
        "Alternate Names": "BCH,Bacau,Baucau,Baukau,Vila Salazar,bao kao,baukau,baw khaw,khet bea kea,\u0411\u0430\u0443\u043a\u0430\u0443,\u05d1\u05d0\u05d5\u05e7\u05d0\u05d5,\u0e1a\u0e32\u0e27\u0e04\u0e32\u0e27,\u0e40\u0e02\u0e15\u0e40\u0e1a\u0e32\u0e40\u0e01\u0e32,\u5305\u8003,\ubc14\uc6b0\uce74\uc6b0",
        "Feature Class": "P",
        "Feature Code": "PPLA",
        "Country Code": "TL",
        "Country name EN": "Timor-Leste",
        "Country Code 2": "",
        "Admin1 Code": "BA",
        "Admin2 Code": "301",
        "Admin3 Code": "30103",
        "Admin4 Code": "",
        "Population": "16000",
        "Elevation": "",
        "DIgital Elevation Model": "442",
        "Timezone": "Asia/Dili",
        "Modification date": "Thu Oct 04 2018 05:30:00 GMT+0530 (India Standard Time)",
        "LABEL EN": "Timor-Leste",
        "latitude": "-8.47572",
        "longitude": "126.45633"
    },
    {
        "Geoname ID": "1645457",
        "Name": "Dili",
        "ASCII Name": "Dili",
        "Alternate Names": "DIL,Delhi,Dilhi,Dili,Dilis,Dilium,Dilli,Dilly,Dilo,Dily,Dyli,D\u00edli,Nova Dili,Ntili,di li,dili,dilli,diri,dly,dyly,tili,\u039d\u03c4\u03af\u03bb\u03b9,\u0414\u0438\u043b\u0438,\u0414\u044b\u043b\u0456,\u0414\u0456\u043b\u0456,\u0534\u056b\u056c\u056b,\u05d3\u05d9\u05dc\u05d9,\u062f\u0644\u064a,\u062f\u0649\u0644\u0649,\u062f\u064a\u0644\u0649,\u062f\u064a\u0644\u064a,\u062f\u06cc\u0644\u06cc,\u0688\u0644\u06cc,\u0921\u093f\u0932\u0940,\u0926\u093f\u0932\u0940,\u09a6\u09bf\u09b2\u09bf,\u0a26\u0a40\u0a32\u0a40,\u0aa6\u0abf\u0ab2\u0ac0,\u0b9f\u0bbf\u0bb2\u0bbf,\u0c26\u0c3f\u0c32\u0c3f,\u0ca1\u0cbf\u0cb2\u0cbf,\u0d26\u0d3f\u0d32\u0d3f,\u0daf\u0dd2\u0dbd\u0dd2,\u0e14\u0e34\u0e25\u0e35,\u0e94\u0eb4\u0ea5\u0eb5,\u0f51\u0fb7\u0f72\u0f0b\u0f63\u0f72\u0f0d,\u1012\u102e\u101c\u102e\u1019\u103c\u102d\u102f\u1037,\u10d3\u10d8\u10da\u10d8,\u12f2\u120a,\u178c\u17b8\u179b\u17b8,\u1c70\u1c64\u1c5e\u1c64,\u30c7\u30a3\u30ea,\u5e1d\u529b,\ub51c\ub9ac",
        "Feature Class": "P",
        "Feature Code": "PPLC",
        "Country Code": "TL",
        "Country name EN": "Timor-Leste",
        "Country Code 2": "",
        "Admin1 Code": "DI",
        "Admin2 Code": "601",
        "Admin3 Code": "60104",
        "Admin4 Code": "",
        "Population": "150000",
        "Elevation": "",
        "DIgital Elevation Model": "3",
        "Timezone": "Asia/Dili",
        "Modification date": "Thu Sep 05 2019 05:30:00 GMT+0530 (India Standard Time)",
        "LABEL EN": "Timor-Leste",
        "latitude": "-8.55861",
        "longitude": "125.57361"
    },
    {
        "Geoname ID": "1942811",
        "Name": "Gleno",
        "ASCII Name": "Gleno",
        "Alternate Names": "Glena,Glenas,Gleno,Glenu,Nkleno,ge lan nu,geullenu,ghlynw,gleno,glnw,glone,glynw,gureno,jlynw,ke lnus,kileno,\u0393\u03ba\u03bb\u03ad\u03bd\u03bf,\u0413\u043b\u0435\u043d\u0443,\u05d2\u05dc\u05e0\u05d5,\u062c\u0644\u064a\u0646\u0648,\u063a\u0644\u064a\u0646\u0648,\u06af\u0644\u06cc\u0646\u0648,\u0917\u094d\u0932\u0947\u0928\u094b,\u0917\u094d\u0932\u094b\u0928\u0947,\u0997\u09cd\u09b2\u09c7\u09a8\u09cb,\u0a97\u0acd\u0ab2\u0ac7\u0aa8\u0acb,\u0b95\u0bbf\u0bb2\u0bc7\u0ba9\u0bca,\u0c17\u0c4d\u0c32\u0c46\u0c28\u0c4b,\u0c97\u0ccd\u0cb2\u0cc6\u0ca8\u0ccb,\u0e40\u0e01\u0e25\u0e19\u0e39\u0e0b,\u30b0\u30ec\u30ce,\u683c\u5170\u5974,\u683c\u862d\u5974,\uae00\ub808\ub204",
        "Feature Class": "P",
        "Feature Code": "PPL",
        "Country Code": "TL",
        "Country name EN": "Timor-Leste",
        "Country Code 2": "",
        "Admin1 Code": "ER",
        "Admin2 Code": "702",
        "Admin3 Code": "70207",
        "Admin4 Code": "",
        "Population": "8133",
        "Elevation": "",
        "DIgital Elevation Model": "709",
        "Timezone": "Asia/Dili",
        "Modification date": "Sun Nov 27 2016 05:30:00 GMT+0530 (India Standard Time)",
        "LABEL EN": "Timor-Leste",
        "latitude": "-8.72389",
        "longitude": "125.43611"
    },
    {
        "Geoname ID": "1637730",
        "Name": "Likis\u00e1",
        "ASCII Name": "Likisa",
        "Alternate Names": "Likisa,Likisia,Likis\u00e1,Liquica,Liquissa,Liqui\u00e7\u00e1,Vila de Liquica,Vila de Liqui\u00e7\u00e1,Vila de liquissa",
        "Feature Class": "P",
        "Feature Code": "PPLA",
        "Country Code": "TL",
        "Country name EN": "Timor-Leste",
        "Country Code 2": "",
        "Admin1 Code": "LI",
        "Admin2 Code": "801",
        "Admin3 Code": "80108",
        "Admin4 Code": "",
        "Population": "19000",
        "Elevation": "",
        "DIgital Elevation Model": "23",
        "Timezone": "Asia/Dili",
        "Modification date": "Wed Jun 10 2020 05:30:00 GMT+0530 (India Standard Time)",
        "LABEL EN": "Timor-Leste",
        "latitude": "-8.5875",
        "longitude": "125.34194"
    },
    {
        "Geoname ID": "1937274",
        "Name": "Lospalos",
        "ASCII Name": "Lospalos",
        "Alternate Names": "Lospalos,Lospalus,loseupalloseu,rosuparosu,sheng bao luo,\u041b\u043e\u0441\u043f\u0430\u043b\u043e\u0441,\u30ed\u30b9\u30d1\u30ed\u30b9,\u8056\u4fdd\u7f85,\ub85c\uc2a4\ud314\ub85c\uc2a4",
        "Feature Class": "P",
        "Feature Code": "PPLA",
        "Country Code": "TL",
        "Country name EN": "Timor-Leste",
        "Country Code 2": "",
        "Admin1 Code": "LA",
        "Admin2 Code": "901",
        "Admin3 Code": "90102",
        "Admin4 Code": "",
        "Population": "17186",
        "Elevation": "",
        "DIgital Elevation Model": "391",
        "Timezone": "Asia/Dili",
        "Modification date": "Fri Oct 05 2018 05:30:00 GMT+0530 (India Standard Time)",
        "LABEL EN": "Timor-Leste",
        "latitude": "-8.52167",
        "longitude": "126.99833"
    },
    {
        "Geoname ID": "1636670",
        "Name": "Maliana",
        "ASCII Name": "Maliana",
        "Alternate Names": "MPT,Maliana,ma li ya na,malliana,malyana,mariana,\u0645\u0627\u0644\u06cc\u0627\u0646\u0627,\u30de\u30ea\u30a2\u30ca,\u746a\u5229\u4e9e\u5a1c,\ub9d0\ub9ac\uc544\ub098",
        "Feature Class": "P",
        "Feature Code": "PPLA",
        "Country Code": "TL",
        "Country name EN": "Timor-Leste",
        "Country Code 2": "",
        "Admin1 Code": "BO",
        "Admin2 Code": "401",
        "Admin3 Code": "40105",
        "Admin4 Code": "",
        "Population": "22000",
        "Elevation": "",
        "DIgital Elevation Model": "253",
        "Timezone": "Asia/Dili",
        "Modification date": "Sun Nov 27 2016 05:30:00 GMT+0530 (India Standard Time)",
        "LABEL EN": "Timor-Leste",
        "latitude": "-8.99167",
        "longitude": "125.21972"
    },
    {
        "Geoname ID": "1636526",
        "Name": "Manatutu",
        "ASCII Name": "Manatutu",
        "Alternate Names": "Manatoetoe,Manatuto,Manatutu,Vila de Manatuto",
        "Feature Class": "P",
        "Feature Code": "PPLA",
        "Country Code": "TL",
        "Country name EN": "Timor-Leste",
        "Country Code 2": "",
        "Admin1 Code": "MT",
        "Admin2 Code": "1101",
        "Admin3 Code": "110104",
        "Admin4 Code": "",
        "Population": "1924",
        "Elevation": "",
        "DIgital Elevation Model": "8",
        "Timezone": "Asia/Dili",
        "Modification date": "Thu Oct 04 2018 05:30:00 GMT+0530 (India Standard Time)",
        "LABEL EN": "Timor-Leste",
        "latitude": "-8.51139",
        "longitude": "126.01306"
    },
    {
        "Geoname ID": "1635826",
        "Name": "Maubara",
        "ASCII Name": "Maubara",
        "Alternate Names": "Maubara,Maubaru,Maubar\u00fa",
        "Feature Class": "P",
        "Feature Code": "PPL",
        "Country Code": "TL",
        "Country name EN": "Timor-Leste",
        "Country Code 2": "",
        "Admin1 Code": "LI",
        "Admin2 Code": "803",
        "Admin3 Code": "80306",
        "Admin4 Code": "",
        "Population": "16300",
        "Elevation": "",
        "DIgital Elevation Model": "21",
        "Timezone": "Asia/Dili",
        "Modification date": "Sun Nov 27 2016 05:30:00 GMT+0530 (India Standard Time)",
        "LABEL EN": "Timor-Leste",
        "latitude": "-8.61194",
        "longitude": "125.20611"
    },
    {
        "Geoname ID": "1635288",
        "Name": "Metinaro",
        "ASCII Name": "Metinaro",
        "Alternate Names": "Met Naro,Metinaro",
        "Feature Class": "P",
        "Feature Code": "PPL",
        "Country Code": "TL",
        "Country name EN": "Timor-Leste",
        "Country Code 2": "",
        "Admin1 Code": "DI",
        "Admin2 Code": "603",
        "Admin3 Code": "60301",
        "Admin4 Code": "",
        "Population": "4000",
        "Elevation": "",
        "DIgital Elevation Model": "15",
        "Timezone": "Asia/Dili",
        "Modification date": "Tue Nov 07 2017 05:30:00 GMT+0530 (India Standard Time)",
        "LABEL EN": "Timor-Leste",
        "latitude": "-8.53007",
        "longitude": "125.74163"
    },
    {
        "Geoname ID": "1632533",
        "Name": "Pante Makasar",
        "ASCII Name": "Pante Makasar",
        "Alternate Names": "Pante Macassar,Pante Makasar,Pante-Makassar,Vila Taveiro",
        "Feature Class": "P",
        "Feature Code": "PPLA",
        "Country Code": "TL",
        "Country name EN": "Timor-Leste",
        "Country Code 2": "",
        "Admin1 Code": "OE",
        "Admin2 Code": "1201",
        "Admin3 Code": "120104",
        "Admin4 Code": "",
        "Population": "4730",
        "Elevation": "",
        "DIgital Elevation Model": "24",
        "Timezone": "Asia/Dili",
        "Modification date": "Sun Nov 27 2016 05:30:00 GMT+0530 (India Standard Time)",
        "LABEL EN": "Timor-Leste",
        "latitude": "-9.2",
        "longitude": "124.38333"
    },
    {
        "Geoname ID": "1628926",
        "Name": "Same",
        "ASCII Name": "Same",
        "Alternate Names": "Same,Vila Filomena da Camara,Vila Filomeno da Camara,Vila Filomeno da C\u00e2mara,sa mu,sa\u06c1m\u06d2  mshrqy tymwr,\u0421\u0430\u043c\u0435,\u0633\u0627\u06c1\u0645\u06d2\u060c \u0645\u0634\u0631\u0642\u06cc \u062a\u06cc\u0645\u0648\u0631,\u85a9\u59c6",
        "Feature Class": "P",
        "Feature Code": "PPLA",
        "Country Code": "TL",
        "Country name EN": "Timor-Leste",
        "Country Code 2": "",
        "Admin1 Code": "MF",
        "Admin2 Code": "1001",
        "Admin3 Code": "100102",
        "Admin4 Code": "",
        "Population": "7500",
        "Elevation": "",
        "DIgital Elevation Model": "481",
        "Timezone": "Asia/Dili",
        "Modification date": "Tue Oct 09 2018 05:30:00 GMT+0530 (India Standard Time)",
        "LABEL EN": "Timor-Leste",
        "latitude": "-9.00417",
        "longitude": "125.64861"
    },
    {
        "Geoname ID": "1626459",
        "Name": "Suai",
        "ASCII Name": "Suai",
        "Alternate Names": "Soeai,Suai,Swai,UAI,su ai,swayy,\u0421\u0443\u0430\u0438,\u0633\u0648\u0627\u0626\u06cc,\u8607\u827e",
        "Feature Class": "P",
        "Feature Code": "PPLA",
        "Country Code": "TL",
        "Country name EN": "Timor-Leste",
        "Country Code 2": "",
        "Admin1 Code": "CO",
        "Admin2 Code": "505",
        "Admin3 Code": "50502",
        "Admin4 Code": "",
        "Population": "21539",
        "Elevation": "",
        "DIgital Elevation Model": "73",
        "Timezone": "Asia/Dili",
        "Modification date": "Sun Nov 27 2016 05:30:00 GMT+0530 (India Standard Time)",
        "LABEL EN": "Timor-Leste",
        "latitude": "-9.31286",
        "longitude": "125.25648"
    },
    {
        "Geoname ID": "1943235",
        "Name": "Venilale",
        "ASCII Name": "Venilale",
        "Alternate Names": "Venilale,Vila Vicosa,Vila Vi\u00e7osa",
        "Feature Class": "P",
        "Feature Code": "PPL",
        "Country Code": "TL",
        "Country name EN": "Timor-Leste",
        "Country Code 2": "",
        "Admin1 Code": "BA",
        "Admin2 Code": "306",
        "Admin3 Code": "30608",
        "Admin4 Code": "",
        "Population": "16000",
        "Elevation": "",
        "DIgital Elevation Model": "834",
        "Timezone": "Asia/Dili",
        "Modification date": "Tue Mar 19 2019 05:30:00 GMT+0530 (India Standard Time)",
        "LABEL EN": "Timor-Leste",
        "latitude": "-8.64306",
        "longitude": "126.37833"
    },
    {
        "Geoname ID": "1622471",
        "Name": "Viqueque",
        "ASCII Name": "Viqueque",
        "Alternate Names": "VIQ,Vikeke,Viqueque,bikeke,wei ke ke,\u0412\u0438\u043a\u0435\u043a\u0435,\u7dad\u514b\u514b,\ube44\ucf00\ucf00",
        "Feature Class": "P",
        "Feature Code": "PPLA",
        "Country Code": "TL",
        "Country name EN": "Timor-Leste",
        "Country Code 2": "",
        "Admin1 Code": "VI",
        "Admin2 Code": "1304",
        "Admin3 Code": "130407",
        "Admin4 Code": "",
        "Population": "6078",
        "Elevation": "",
        "DIgital Elevation Model": "55",
        "Timezone": "Asia/Dili",
        "Modification date": "Wed Nov 28 2018 05:30:00 GMT+0530 (India Standard Time)",
        "LABEL EN": "Timor-Leste",
        "latitude": "-8.8575",
        "longitude": "126.36472"
    }
]